{
    "Ar36": {
        "error": 0.00027652287239805166, 
        "fit": "parabolic", 
        "value": 0.014494534552068417
    }, 
    "Ar37": {
        "error": 0.013153618788178239, 
        "fit": "linear", 
        "value": -0.033300585670302106
    }, 
    "Ar38": {
        "error": 0.014435119165976751, 
        "fit": "linear", 
        "value": 0.094779221760843524
    }, 
    "Ar39": {
        "error": 0.010083469532969555, 
        "fit": "parabolic", 
        "value": 22.735210165371019
    }, 
    "Ar40": {
        "error": 0.069933015943736951, 
        "fit": "parabolic", 
        "value": 1474.3040158524723
    }, 
    "Ar41": {
        "error": 0.0065762077932859974, 
        "fit": "average", 
        "value": -0.013633180482429452
    }
}